staticsites/__init__.py
staticsites/admin.py
staticsites/conf.py
staticsites/conf_dict.py
staticsites/decorators.py
staticsites/deploy.py
staticsites/django-static-admin.py
staticsites/minify.py
staticsites/models.py
staticsites/utilities.py
staticsites/management/__init__.py
staticsites/management/commands/__init__.py
staticsites/management/commands/deploy.py
staticsites/management/commands/runserver.py
staticsites/management/commands/startproject.py
staticsites/management/commands/startsite.py
staticsites/migrations/0001_initial.py
staticsites/migrations/__init__.py
staticsites/templates/project_template/manage.py-tpl
staticsites/templates/project_template/project_name/__init__.py-tpl
staticsites/templates/project_template/project_name/settings.py-tpl
staticsites/templates/project_template/project_name/urls.py-tpl
staticsites/templates/project_template/project_name/wsgi.py-tpl
staticsites/templates/site_template/__init__.py-tpl
staticsites/templates/site_template/admin.py-tpl
staticsites/templates/site_template/apps.py-tpl
staticsites/templates/site_template/models.py-tpl
staticsites/templates/site_template/tests.py-tpl
staticsites/templates/site_template/views.py-tpl
staticsites/templates/site_template/migrations/__init__.py-tpl
staticsites/tests/__init__.py
staticsites/tests/settings.py
staticsites/tests/tests.py
staticsites/tests/urls.py
staticsites/tests/wsgi.py
staticsites/tests/samples/__init__.py
staticsites/tests/samples/01_hello_world/__init__.py
staticsites/tests/samples/01_hello_world/settings.py
staticsites/tests/samples/01_hello_world/views.py
staticsites/tests/samples/02_hello_world/__init__.py
staticsites/tests/samples/02_hello_world/settings.py
staticsites/tests/samples/02_hello_world/views.py
staticsites/tests/samples/03_aws/__init__.py
staticsites/tests/samples/03_aws/settings.py
staticsites/tests/samples/03_aws/views.py
staticsites/tests/samples/04_aws_multiple_deploy_type/__init__.py
django_static_sites-0.0.8.dist-info/LICENSE
django_static_sites-0.0.8.dist-info/METADATA
django_static_sites-0.0.8.dist-info/WHEEL
django_static_sites-0.0.8.dist-info/entry_points.txt
django_static_sites-0.0.8.dist-info/top_level.txt
django_static_sites-0.0.8.dist-info/RECORD
