Metadata-Version: 2.1
Name: django-static-sites
Version: 0.0.8
Summary: An easy to use Django app to make static site.
Home-page: https://github.com/ciotto/django-static-sites
Author: Christian Bianciotto
Author-email: info@ci8.it
License: GNU GENERAL PUBLIC LICENSE
Platform: UNKNOWN
Classifier: Environment :: Web Environment
Classifier: Framework :: Django
Classifier: Intended Audience :: Developers
Classifier: License :: OSI Approved :: MIT License
Classifier: Operating System :: OS Independent
Classifier: Programming Language :: Python
Classifier: Programming Language :: Python :: 2.7
Requires-Dist: Django (<1.10,>=1.9)
Requires-Dist: htmlmin (==0.1.6)
Requires-Dist: slimit (==0.8.1)
Requires-Dist: ply (==3.4)
Requires-Dist: csscompressor (==0.9.4)
